netograph/__init__.py
netograph/dsetapi/__init__.py
netograph/dsetapi/dset_pb2.py
netograph/dsetapi/dset_pb2_grpc.py
netograph/userapi/__init__.py
netograph/userapi/user_pb2.py
netograph/userapi/user_pb2_grpc.py
netograph-0.5.1.dist-info/METADATA
netograph-0.5.1.dist-info/WHEEL
netograph-0.5.1.dist-info/top_level.txt
netograph-0.5.1.dist-info/RECORD
