Metadata-Version: 2.1
Name: netograph
Version: 0.5.1
Summary: A Python interface to netograph.io.
Home-page: https://netograph.io
Author: Netograph Ltd
Author-email: aldo@netograph.io
License: UNKNOWN
Platform: UNKNOWN
Requires-Dist: grpcio (>=1.13)
Requires-Dist: googleapis-common-protos
Provides-Extra: dev
Requires-Dist: grpcio-tools; extra == 'dev'
Requires-Dist: flake8; extra == 'dev'
